game_resolver/__init__.py
game_resolver/examples/__init__.py
game_resolver/examples/battle_of_sex.py
game_resolver/examples/courno_game.py
game_resolver/examples/hawk_dove_game.py
game_resolver/examples/prisoners_dilemma.py
game_resolver/game.py
game_resolver/nash_equilibrium.py
game_resolver/payoff.py
game_resolver/player.py
game_resolver/util/__init__.py
game_resolver/util/cartesian_product.py
game_resolver/util/logger.py
game_resolver-0.3.1.dist-info/METADATA
game_resolver-0.3.1.dist-info/WHEEL
game_resolver-0.3.1.dist-info/RECORD
