Metadata-Version: 2.1
Name: game_resolver
Version: 0.3.1
Summary: 
License: MIT
Author: nariaki-nishino
Requires-Python: >=3.11,<4.0
Classifier: License :: OSI Approved :: MIT License
Classifier: Programming Language :: Python :: 3
Classifier: Programming Language :: Python :: 3.11
Classifier: Programming Language :: Python :: 3.12
Requires-Dist: numpy (>=1.22.3,<2.0.0)
